jsonview/__init__.py
jsonview/decorators.py
jsonview/exceptions.py
jsonview/models.py
jsonview/tests.py
jsonview/views.py
django_jsonview-1.3.1.dist-info/LICENSE
django_jsonview-1.3.1.dist-info/METADATA
django_jsonview-1.3.1.dist-info/WHEEL
django_jsonview-1.3.1.dist-info/top_level.txt
django_jsonview-1.3.1.dist-info/RECORD
